idroman/__init__.py
idroman/roman.py
idroman-0.2.1.dist-info/licenses/LICENCE
idroman-0.2.1.dist-info/METADATA
idroman-0.2.1.dist-info/WHEEL
idroman-0.2.1.dist-info/top_level.txt
idroman-0.2.1.dist-info/RECORD
