Metadata-Version: 2.4
Name: idroman
Version: 0.2.1
Summary: A module for converting between integers and roman literals.
Author-email: Improper Decoherence <improper.decoherence@proton.me>
License: MIT License
Project-URL: Homepage, https://codeberg.org/decoherence/idroman
Classifier: Programming Language :: Python :: 3
Classifier: License :: OSI Approved :: MIT License
Classifier: Operating System :: OS Independent
Requires-Python: >=3.12
License-File: LICENCE
Provides-Extra: test
Requires-Dist: pytest>=8.4; extra == "test"
Dynamic: license-file
